[{"time": 0.013822317123413086, "Force": [0.0, -0.0], "Force_locked_cable": [0.0, 0.0], "Force_wall": [0.0, 0.0], "mouse_pos": [399, 142], "end_pos": [399, 142], "shocks": 0, "score": -0.013825654983520508, "assist_active": true, "special_active": true, "condition": "dynamic", "user_id": 1, "trial_num": 15}, {"time": 0.027616262435913086, "Force": [0.0, -0.0], "Force_locked_cable": [0.0, 0.0], "Force_wall": [0.0, 0.0], "mouse_pos": [399, 142], "end_pos": [399, 142], "shocks": 0, "score": -0.02761983871459961, "assist_active": true, "special_active": true, "condition": "dynamic", "user_id": 1, "trial_num": 15}, {"time": 0.04159951210021973, "Force": [0.0, -0.0], "Force_locked_cable": [0.0, 0.0], "Force_wall": [0.0, 0.0], "mouse_pos": [399, 142], "end_pos": [399, 142], "shocks": 0, "score": -0.041603803634643555, "assist_active": true, "special_active": true, "condition": "dynamic", "user_id": 1, "trial_num": 15}, {"time": 0.05517244338989258, "Force": [0.0, -0.0], "Force_locked_cable": [0.0, 0.0], "Force_wall": [0.0, 0.0], "mouse_pos": [399, 142], "end_pos": [399, 142], "shocks": 0, "score": -0.0551762580871582, "assist_active": true, "special_active": true, "condition": "dynamic", "user_id": 1, "trial_num": 15}, {"time": 0.0690147876739502, "Force": [0.0, -0.0], "Force_locked_cable": [0.0, 0.0], "Force_wall": [0.0, 0.0], "mouse_pos": [399, 142], "end_pos": [399, 142], "shocks": 0, "score": -0.06901860237121582, "assist_active": true, "special_active": true, "condition": "dynamic", "user_id": 1, "trial_num": 15}, {"time": 0.08270502090454102, "Force": [0.0, -0.0], "Force_locked_cable": [0.0, 0.0], "Force_wall": [0.0, 0.0], "mouse_pos": [399, 142], "end_pos": [399, 142], "shocks": 0, "score": -0.08270883560180664, "assist_active": true, "special_active": true, "condition": "dynamic", "user_id": 1, "trial_num": 15}, {"time": 0.0964202880859375, "Force": [0.0, -0.0], "Force_locked_cable": [0.0, 0.0], "Force_wall": [0.0, 0.0], "mouse_pos": [399, 142], "end_pos": [399, 142], "shocks": 0, "score": -0.09642362594604492, "assist_active": true, "special_active": true, "condition": "dynamic", "user_id": 1, "trial_num": 15}, {"time": 0.11007165908813477, "Force": [0.0, -0.0], "Force_locked_cable": [0.0, 0.0], "Force_wall": [0.0, 0.0], "mouse_pos": [399, 142], "end_pos": [399, 142], "shocks": 0, "score": -0.11007499694824219, "assist_active": true, "special_active": true, "condition": "dynamic", "user_id": 1, "trial_num": 15}, {"time": 0.1242361068725586, "Force": [0.0, -0.0], "Force_locked_cable": [0.0, 0.0], "Force_wall": [0.0, 0.0], "mouse_pos": [399, 142], "end_pos": [399, 142], "shocks": 0, "score": -0.12424278259277344, "assist_active": true, "special_active": true, "condition": "dynamic", "user_id": 1, "trial_num": 15}, {"time": 0.1379542350769043, "Force": [0.0, -0.0], "Force_locked_cable": [0.0, 0.0], "Force_wall": [0.0, 0.0], "mouse_pos": [399, 142], "end_pos": [399, 142], "shocks": 0, "score": -0.13795709609985352, "assist_active": true, "special_active": true, "condition": "dynamic", "user_id": 1, "trial_num": 15}]