[{"time": 0.013257980346679688, "Force": [0.0, -0.0], "Force_locked_cable": [0.0, 0.0], "Force_wall": [0.0, 0.0], "mouse_pos": [282, 195], "end_pos": [282, 195], "shocks": 0, "score": -0.013262033462524414, "assist_active": false, "special_active": false, "condition": "baseline", "user_id": 8, "trial_num": 12}, {"time": 0.02660369873046875, "Force": [0.0, -0.0], "Force_locked_cable": [0.0, 0.0], "Force_wall": [0.0, 0.0], "mouse_pos": [282, 195], "end_pos": [282, 195], "shocks": 0, "score": -0.026607275009155273, "assist_active": false, "special_active": false, "condition": "baseline", "user_id": 8, "trial_num": 12}, {"time": 0.03966355323791504, "Force": [0.0, -0.0], "Force_locked_cable": [0.0, 0.0], "Force_wall": [0.0, 0.0], "mouse_pos": [282, 195], "end_pos": [282, 195], "shocks": 0, "score": -0.03966641426086426, "assist_active": false, "special_active": false, "condition": "baseline", "user_id": 8, "trial_num": 12}, {"time": 0.052617788314819336, "Force": [0.0, -0.0], "Force_locked_cable": [0.0, 0.0], "Force_wall": [0.0, 0.0], "mouse_pos": [282, 195], "end_pos": [282, 195], "shocks": 0, "score": -0.05262112617492676, "assist_active": false, "special_active": false, "condition": "baseline", "user_id": 8, "trial_num": 12}, {"time": 0.06583929061889648, "Force": [0.0, -0.0], "Force_locked_cable": [0.0, 0.0], "Force_wall": [0.0, 0.0], "mouse_pos": [282, 195], "end_pos": [282, 195], "shocks": 0, "score": -0.06584310531616211, "assist_active": false, "special_active": false, "condition": "baseline", "user_id": 8, "trial_num": 12}, {"time": 0.07891559600830078, "Force": [0.0, -0.0], "Force_locked_cable": [0.0, 0.0], "Force_wall": [0.0, 0.0], "mouse_pos": [282, 195], "end_pos": [282, 195], "shocks": 0, "score": -0.07891845703125, "assist_active": false, "special_active": false, "condition": "baseline", "user_id": 8, "trial_num": 12}]